CHANGES.rst
CONTRIBUTORS.rst
MANIFEST.in
README.rst
setup.cfg
setup.py
docs/LICENSE.GPL
docs/LICENSE.rst
docs/index.rst
src/plonetheme/__init__.py
src/plonetheme.persona.egg-info/PKG-INFO
src/plonetheme.persona.egg-info/SOURCES.txt
src/plonetheme.persona.egg-info/dependency_links.txt
src/plonetheme.persona.egg-info/entry_points.txt
src/plonetheme.persona.egg-info/namespace_packages.txt
src/plonetheme.persona.egg-info/not-zip-safe
src/plonetheme.persona.egg-info/requires.txt
src/plonetheme.persona.egg-info/top_level.txt
src/plonetheme/persona/__init__.py
src/plonetheme/persona/configure.zcml
src/plonetheme/persona/interfaces.py
src/plonetheme/persona/profiles/default/browserlayer.xml
src/plonetheme/persona/profiles/default/metadata.xml
src/plonetheme/persona/profiles/default/registry.xml
src/plonetheme/persona/profiles/default/skins.xml
src/plonetheme/persona/profiles/default/theme.xml
src/plonetheme/persona/profiles/uninstall/browserlayer.xml
src/plonetheme/persona/profiles/uninstall/registry.xml
src/plonetheme/persona/profiles/uninstall/theme.xml
src/plonetheme/persona/theme/backend.xml
src/plonetheme/persona/theme/index.html
src/plonetheme/persona/theme/manifest.cfg
src/plonetheme/persona/theme/persona-apple-touch-icon-114x114-precomposed.png
src/plonetheme/persona/theme/persona-apple-touch-icon-144x144-precomposed.png
src/plonetheme/persona/theme/persona-apple-touch-icon-57x57-precomposed.png
src/plonetheme/persona/theme/persona-apple-touch-icon-72x72-precomposed.png
src/plonetheme/persona/theme/persona-apple-touch-icon-precomposed.png
src/plonetheme/persona/theme/persona-apple-touch-icon.png
src/plonetheme/persona/theme/persona-favicon.ico
src/plonetheme/persona/theme/preview.png
src/plonetheme/persona/theme/rules.xml
src/plonetheme/persona/theme/css/persona-compiled.css
src/plonetheme/persona/theme/css/persona-compiled.css.map
src/plonetheme/persona/theme/fonts/persona-fontello-config.json
src/plonetheme/persona/theme/fonts/persona-fontello.eot
src/plonetheme/persona/theme/fonts/persona-fontello.svg
src/plonetheme/persona/theme/fonts/persona-fontello.ttf
src/plonetheme/persona/theme/fonts/persona-fontello.woff
src/plonetheme/persona/theme/fonts/lato/1YwB1sO8YE1Lyjf12WNiUA.woff2
src/plonetheme/persona/theme/fonts/lato/2HG_tEPiQ4Z6795cGfdivD8E0i7KZn-EPnyo3HZu7kw.woff
