Metadata-Version: 1.1
Name: plonetheme.persona
Version: 1.0a1
Summary: The Persona Theme for Plone 5.
Home-page: https://pypi.python.org/pypi/plonetheme.persona
Author: Rene Jochum
Author-email: rene@jochums.at
License: GPL version 2
Keywords: Python Plone
Platform: UNKNOWN
Classifier: Environment :: Web Environment
Classifier: Framework :: Plone
Classifier: Framework :: Plone :: 5.0
Classifier: Programming Language :: Python
Classifier: Programming Language :: Python :: 2.7
Classifier: Operating System :: OS Independent
Classifier: License :: OSI Approved :: GNU General Public License v2 (GPLv2)
